ugbib_tkinter/__init__.py
ugbib_tkinter/bibForm.py
ugbib_tkinter-1.3.8.dist-info/METADATA
ugbib_tkinter-1.3.8.dist-info/WHEEL
ugbib_tkinter-1.3.8.dist-info/licenses/LICENSE
ugbib_tkinter-1.3.8.dist-info/licenses/LICENSE~
ugbib_tkinter-1.3.8.dist-info/RECORD
