Metadata-Version: 2.4
Name: ugbib_tkinter
Version: 1.3.8
Summary: Formulare für PostgreSQL Daten
Author-email: Ulrich Goebel <ulrich@fam-goebel.de>
License: MIT License
License-File: LICENSE
License-File: LICENSE~
Classifier: Development Status :: 5 - Production/Stable
Classifier: Programming Language :: Python :: 3
Classifier: Programming Language :: Python :: 3.10
Requires-Python: >=3.10
Requires-Dist: pillow
Requires-Dist: pyyaml
Requires-Dist: ugbib-werkzeug
